{
    "$schema": "https://vega.github.io/schema/vega-lite/v5.json",
    "title": "Percentage of People that Never Smoked in Australia for 2001",
    "width": 600,
    "height": 600,
    "projection": {"type": "equirectangular"},
    "data": {
      "url": "https://raw.githubusercontent.com/stha0035/Assingment2-2977275/main/AustralianStates%20(6).topojson",
      "format": {"type": "topojson", "feature": "AustralianStates"}
    },
    "transform": [
        {
        "lookup": "properties.STATE_NAME",
        "from": {
        "data": {
        "url": "https://raw.githubusercontent.com/stha0035/Assingment2-2977275/main/UpdatedTabacoo2001-2019.csv"
        },
            "key": "State",
            "fields": ["Smoking status","2001"]
        }
        }
        ],
        "mark": {"type": "geoshape"},
        "encoding": {
            "color": {
                "field": "2001",
                "type": "quantitative",
                "scale": {"scheme": "blues"}
                
        },
        "tooltip": [
            {"field": "properties.STATE_NAME", "type": "nominal", "title": "State Name"},
            {"field": "Smoking status", "type": "nominal"},
            {"field": "2001", "type": "quantitative"}
           
        ]
        }
  }

  